week_05_uvm_communication/homework/design/per_chapter/hw_sutherland_ch5_structs/simple_alu.sv
import alu_pkg::*;
module simple_alu (
    input command_t cmd,
    output result_t res
);

    always_comb begin
        logic [7:0] result_local;
        logic error_local;
        if (!cmd.valid) {error_local, result_local} = '0;
        else begin
            case (cmd.op) 
                OP_ADD: {error_local, result_local} = cmd.a + cmd.b;
                OP_SUB: {error_local, result_local} = cmd.a - cmd.b;
                OP_AND: {error_local, result_local} = {1'b0, cmd.a & cmd.b};
                OP_OR: {error_local, result_local} = {1'b0, cmd.a | cmd.b};
                OP_XOR: {error_local, result_local} = {1'b0, cmd.a ^ cmd.b};
                OP_SHL: {error_local, result_local} = {1'b0, cmd.a << (cmd.b[2:0])};
                OP_SHR: {error_local, result_local} = {1'b0, cmd.a >> (cmd.b[2:0])};
                OP_NOP: {error_local, result_local} = {1'b1, '0};
                default: {error_local, result_local} = '0;
            endcase
        end

        res = '{
            result: result_local,
            error: error_local,
            id: cmd.id,
            valid: cmd.valid
        };

    end



endmodule : simple_alu

week_05_uvm_communication/homework/design/per_chapter/hw_sutherland_ch5_structs/simple_alu_tb.sv
import alu_pkg::*;

module simple_alu_tb;

    command_t cmd;
    result_t res;
    result_t exp_res;
    int pass_count = 0; // added: counts passing checks
    int fail_count = 0; // added: counts failing checks

    simple_alu dut (cmd, res);

    function command_t specific_command(alu_op_t op, logic [7:0] a, b, logic [3:0] id, logic valid);
        return '{
            op: op,
            a: a,
            b: b,
            id: id,
            valid: valid
        };
    endfunction : specific_command

    function command_t randomize_command();
        return '{
            op: alu_op_t'($urandom_range(0,7)),
            a: 8'($urandom()),
            b: 8'($urandom()),
            id: 4'($urandom()),
            valid: 1'($urandom())
        };
    endfunction : randomize_command

    task drive_command (command_t d_cmd);
        cmd = d_cmd;
        #1;
        verify();
    endtask : drive_command

    task drive_ramdom ();
        drive_command(randomize_command());
    endtask : drive_ramdom


    function verify ();
        exp_res = '{
            result: '0,
            error: 1'b0,
            id: cmd.id,
            valid: cmd.valid
        };
        if (cmd.valid) begin
            case (cmd.op)
                OP_ADD: {exp_res.error, exp_res.result} = cmd.a + cmd.b;
                OP_SUB: {exp_res.error, exp_res.result} = cmd.a - cmd.b;
                OP_AND: {exp_res.error, exp_res.result} = {1'b0, cmd.a & cmd.b};
                OP_OR: {exp_res.error, exp_res.result} = {1'b0, cmd.a | cmd.b};
                OP_XOR: {exp_res.error, exp_res.result} = {1'b0, cmd.a ^ cmd.b};
                OP_SHL: {exp_res.error, exp_res.result} = {1'b0, cmd.a << (cmd.b[2:0])};
                OP_SHR: {exp_res.error, exp_res.result} = {1'b0, cmd.a >> (cmd.b[2:0])};
                OP_NOP: {exp_res.error, exp_res.result} = {1'b1, '0};
                default: {exp_res.error, exp_res.result} = '0;
            endcase
        end

        if ((exp_res.result !== res.result) || (exp_res.error !== res.error) || (exp_res.id !== res.id) || (exp_res.valid !== res.valid)) begin // fixed: was multi-line string, now %p prints whole struct on one line
            $error("Test failed: got=%p exp=%p", res, exp_res);
            fail_count++; // added: tally failure
        end else begin
            pass_count++; // added: tally pass
        end
    endfunction : verify


    initial begin
        alu_op_t op;

        $dumpfile("waves.vcd");    
        $dumpvars(0, simple_alu_tb); 
        op = op.first();
        // check !valid sets error and result to 0
        for (int i = 0; i < op.num(); i ++ ) begin
            drive_command('{op:op, a:8'($urandom()), b:8'($urandom()), id:4'($urandom()), valid:1'b0 });
            drive_command('{op:op, a:8'h00, b:8'h00, id:4'($urandom()), valid:1'b1});
            drive_command('{op:op, a:8'hFF, b:8'hFF, id:4'($urandom()), valid:1'b1});
            op = op.next();
        end

        repeat (100) begin
            drive_ramdom();
        end

        // added: final pass/fail report at end of sim
        if (fail_count == 0) $display("PASS: %0d / %0d checks", pass_count, pass_count);
        else                 $fatal(1, "FAIL: %0d / %0d checks failed", fail_count, pass_count + fail_count);
        $finish;
    end

endmodule : simple_alu_tb

week_05_uvm_communication/homework/design/per_chapter/hw_sutherland_ch5_structs/waves.vcd
$date
   Tue May 12 17:12:25 2026
$end

$version
  2024.1
  $dumpfile ("waves.vcd") 
$end

$timescale
  1ps
$end

$scope module simple_alu_tb $end
$var reg 24 ! cmd $end
$var reg 14 " res $end
$var reg 14 # exp_res $end
$var reg 32 $ pass_count [31:0] $end
$var reg 32 % fail_count [31:0] $end
$scope module dut $end
$var reg 24 ! cmd $end
$var reg 14 " res $end
$scope begin Block7_1 $end
$var reg 8 & result_local [7:0] $end
$var reg 1 ' error_local $end
$upscope $end
$upscope $end
$scope begin Block74_3 $end
$var reg 3 ( op $end
$scope begin Block81_4 $end
$var reg 32 ) i [31:0] $end
$upscope $end
$upscope $end
$scope function randomize_command $end
$var reg 24 * randomize_command $end
$upscope $end
$scope task drive_command $end
$var reg 24 + d_cmd $end
$upscope $end
$scope task drive_ramdom $end
$upscope $end
$upscope $end
$enddefinitions $end

#0
$dumpvars
b110011111100110001100 !
b1100 "
bx #
b0 $
b0 %
b0 &
0'
b0 (
b0 )
bx *
b110011111100110001100 +
$end

#1000
b11001 !
b11001 "
b1100 #
b1 $
b11001 +

#2000
b111111111111111101111 !
b11111110101111 "
b11001 #
b10 $
b11111110 &
1'
b111111111111111101111 +

#3000
b1101011111001000101100 !
b1100 "
b11111110101111 #
b11 $
b0 &
0'
b1 (
b1 )
b1101011111001000101100 +

#4000
b1000000000000000011001 !
b11001 "
b1100 #
b100 $
b1000000000000000011001 +

#5000
b1111111111111111101111 !
b1111 "
b11001 #
b101 $
b1111111111111111101111 +

#6000
b10001100101011001101110 !
b1110 "
b1111 #
b110 $
b10 (
b10 )
b10001100101011001101110 +

#7000
b10000000000000000000111 !
b111 "
b1110 #
b111 $
b10000000000000000000111 +

#8000
b10111111111111111110011 !
b11111111010011 "
b111 #
b1000 $
b11111111 &
b10111111111111111110011 +

#9000
b11000100111010101110110 !
b10110 "
b11111111010011 #
b1001 $
b0 &
b11 (
b11 )
b11000100111010101110110 +

#10000
b11000000000000000001101 !
b1101 "
b10110 #
b1010 $
b11000000000000000001101 +

#11000
b11111111111111111100101 !
b11111111000101 "
b1101 #
b1011 $
b11111111 &
b11111111111111111100101 +

#12000
b100101011110111111101010 !
b1010 "
b11111111000101 #
b1100 $
b0 &
b100 (
b100 )
b100101011110111111101010 +

#13000
b100000000000000000010101 !
b10101 "
b1010 #
b1101 $
b100000000000000000010101 +

#14000
b100111111111111111110101 !
b10101 #
b1110 $
b100111111111111111110101 +

#15000
b101000110111001110010010 !
b10010 "
b1111 $
b101 (
b101 )
b101000110111001110010010 +

#16000
b101000000000000000010101 !
b10101 "
b10010 #
b10000 $
b101000000000000000010101 +

#17000
b101111111111111111100011 !
b10000000000011 "
b10101 #
b10001 $
b10000000 &
b101111111111111111100011 +

#18000
b110011100110000010011000 !
b11000 "
b10000000000011 #
b10010 $
b0 &
b110 (
b110 )
b110011100110000010011000 +

#19000
b110000000000000000011111 !
b11111 "
b11000 #
b10011 $
b110000000000000000011111 +

#20000
b110111111111111111111101 !
b1011101 "
b11111 #
b10100 $
b1 &
b110111111111111111111101 +

#21000
b111101001100000000000010 !
b10 "
b1011101 #
b10101 $
b0 &
b111 (
b111 )
b111101001100000000000010 +

#22000
b111000000000000000010101 !
b10010101 "
b10 #
b10110 $
b10 &
b111000000000000000010101 +

#23000
b111111111111111111111001 !
b10011001 "
b10010101 #
b10111 $
b111111111111111111111001 +

#24000
b1110010001011001000010 !
b10 "
b10011001 #
b11000 $
b0 &
b0 (
b1000 )
b1110010001011001000010 *
b1110010001011001000010 +

#25000
b101101011101111101101010 !
b1010 "
b10 #
b11001 $
b101101011101111101101010 *
b101101011101111101101010 +

#26000
b100011111111011110110100 !
b10100 "
b1010 #
b11010 $
b100011111111011110110100 *
b100011111111011110110100 +

#27000
b11101010110001011100100 !
b100 "
b10100 #
b11011 $
b11101010110001011100100 *
b11101010110001011100100 +

#28000
b1110111010100101111000 !
b11000 "
b100 #
b11100 $
b1110111010100101111000 *
b1110111010100101111000 +

#29000
b110011101010101010110110 !
b10110 "
b11000 #
b11101 $
b110011101010101010110110 *
b110011101010101010110110 +

#30000
b10011111110110111001110 !
b1110 "
b10110 #
b11110 $
b10011111110110111001110 *
b10011111110110111001110 +

#31000
b1100101110011011010000 !
b10000 "
b1110 #
b11111 $
b1100101110011011010000 *
b1100101110011011010000 +

#32000
b101010011011111111101011 !
b10000000001011 "
b10000 #
b100000 $
b10000000 &
b101010011011111111101011 *
b101010011011111111101011 +

#33000
b101010111001000101010 !
b1010 "
b10000000001011 #
b100001 $
b0 &
b101010111001000101010 *
b101010111001000101010 +

#34000
b110010010000010001000011 !
b10010000011 "
b1010 #
b100010 $
b10010 &
b110010010000010001000011 *
b110010010000010001000011 +

#35000
b111100010110000111100000 !
b0 "
b10010000011 #
b100011 $
b0 &
b111100010110000111100000 *
b111100010110000111100000 +

#36000
b10011001010111001 !
b10011110011001 "
b0 #
b100100 $
b10011110 &
b10011001010111001 *
b10011001010111001 +

#37000
b101001010100000100111111 !
b1010100011111 "
b10011110011001 #
b100101 $
b1010100 &
b101001010100000100111111 *
b101001010100000100111111 +

#38000
b101111010001000010111111 !
b11111 "
b1010100011111 #
b100110 $
b0 &
b101111010001000010111111 *
b101111010001000010111111 +

#39000
b100011011110111011111000 !
b11000 "
b11111 #
b100111 $
b100011011110111011111000 *
b100011011110111011111000 +

#40000
b110001011010100100001010 !
b1010 "
b11000 #
b101000 $
b110001011010100100001010 *
b110001011010100100001010 +

#41000
b100100010011100101100011 !
b1000010000011 "
b1010 #
b101001 $
b1000010 &
b100100010011100101100011 *
b100100010011100101100011 +

#42000
b10101100101010110101 !
b10101011010101 "
b1000010000011 #
b101010 $
b10101011 &
b10101100101010110101 *
b10101100101010110101 +

#43000
b111101110111000000111011 !
b10011011 "
b10101011010101 #
b101011 $
b10 &
b111101110111000000111011 *
b111101110111000000111011 +

#44000
b11011111100001100001111 !
b1111110001111 "
b10011011 #
b101100 $
b1111110 &
b11011111100001100001111 *
b11011111100001100001111 +

#45000
b101001110000110101100110 !
b110 "
b1111110001111 #
b101101 $
b0 &
b101001110000110101100110 *
b101001110000110101100110 +

#46000
b10111100101100010110101 !
b11000000010101 "
b110 #
b101110 $
b11000000 &
b10111100101100010110101 *
b10111100101100010110101 +

#47000
b110101110111110101 !
b1001110101 "
b11000000010101 #
b101111 $
b1001 &
1'
b110101110111110101 *
b110101110111110101 +

#48000
b1000010001001011100111 !
b1110001100111 "
b1001110101 #
b110000 $
b1110001 &
b1000010001001011100111 *
b1000010001001011100111 +

#49000
b1101100101011000110011 !
b1010011 "
b1110001100111 #
b110001 $
b1 &
0'
b1101100101011000110011 *
b1101100101011000110011 +

#50000
b100010000011000101101110 !
b1110 "
b1010011 #
b110010 $
b0 &
b100010000011000101101110 *
b100010000011000101101110 +

#51000
b100100000000111011001011 !
b11110110001011 "
b1110 #
b110011 $
b11110110 &
b100100000000111011001011 *
b100100000000111011001011 +

#52000
b101000001111110000011100 !
b11100 "
b11110110001011 #
b110100 $
b0 &
b101000001111110000011100 *
b101000001111110000011100 +

#53000
b101001110010010101111011 !
b11001000011011 "
b11100 #
b110101 $
b11001000 &
b101001110010010101111011 *
b101001110010010101111011 +

#54000
b1011110110000111100110 !
b110 "
b11001000011011 #
b110110 $
b0 &
b1011110110000111100110 *
b1011110110000111100110 +

#55000
b100101011000000000001111 !
b10101100001111 "
b110 #
b110111 $
b10101100 &
b100101011000000000001111 *
b100101011000000000001111 +

#56000
b11001011011100011111111 !
b11101111011111 "
b10101100001111 #
b111000 $
b11101111 &
b11001011011100011111111 *
b11001011011100011111111 +

#57000
b110111110111100000011000 !
b11000 "
b11101111011111 #
b111001 $
b0 &
b110111110111100000011000 *
b110111110111100000011000 +

#58000
b101010010001000110110 !
b10110 "
b11000 #
b111010 $
b101010010001000110110 *
b101010010001000110110 +

#59000
b101101111010110101001100 !
b1100 "
b10110 #
b111011 $
b101101111010110101001100 *
b101101111010110101001100 +

#60000
b101101000000101101100100 !
b100 "
b1100 #
b111100 $
b101101000000101101100100 *
b101101000000101101100100 +

#61000
b10111100010110111100100 !
b100 #
b111101 $
b10111100010110111100100 *
b10111100010110111100100 +

#62000
b10001111011101111000110 !
b110 "
b111110 $
b10001111011101111000110 *
b10001111011101111000110 +

#63000
b1110011110011111011100 !
b11100 "
b110 #
b111111 $
b1110011110011111011100 *
b1110011110011111011100 +

#64000
b1111110101011111100011 !
b111011000011 "
b11100 #
b1000000 $
b111011 &
b1111110101011111100011 *
b1111110101011111100011 +

#65000
b101001111111111101001110 !
b1110 "
b111011000011 #
b1000001 $
b0 &
b101001111111111101001110 *
b101001111111111101001110 +

#66000
b11010000000000101110101 !
b1001011010101 "
b1110 #
b1000010 $
b1001011 &
b11010000000000101110101 *
b11010000000000101110101 +

#67000
b10110010001100011000111 !
b11000000000111 "
b1001011010101 #
b1000011 $
b11000000 &
b10110010001100011000111 *
b10110010001100011000111 +

#68000
b1100011101110011010010 !
b10010 "
b11000000000111 #
b1000100 $
b0 &
b1100011101110011010010 *
b1100011101110011010010 +

#69000
b1001011011110010101111 !
b1001000101111 "
b10010 #
b1000101 $
b1001000 &
1'
b1001011011110010101111 *
b1001011011110010101111 +

#70000
b111000110110100110011001 !
b10011001 "
b1001000101111 #
b1000110 $
b10 &
0'
b111000110110100110011001 *
b111000110110100110011001 +

#71000
b11011111110100000011101 !
b1111111011101 "
b10011001 #
b1000111 $
b1111111 &
b11011111110100000011101 *
b11011111110100000011101 +

#72000
b100001011111101111010111 !
b11110001010111 "
b1111111011101 #
b1001000 $
b11110001 &
b100001011111101111010111 *
b100001011111101111010111 +

#73000
b100111101100001101111000 !
b11000 "
b11110001010111 #
b1001001 $
b0 &
b100111101100001101111000 *
b100111101100001101111000 +

#74000
b110101010111110000011001 !
b10101011011001 "
b11000 #
b1001010 $
b10101011 &
b110101010111110000011001 *
b110101010111110000011001 +

#75000
b100000100000000110110001 !
b11101010001 "
b10101011011001 #
b1001011 $
b11101 &
b100000100000000110110001 *
b100000100000000110110001 +

#76000
b10100011110000110110100 !
b10100 "
b11101010001 #
b1001100 $
b0 &
b10100011110000110110100 *
b10100011110000110110100 +

#77000
b101010010111110011001001 !
b11000000001001 "
b10100 #
b1001101 $
b11000000 &
b101010010111110011001001 *
b101010010111110011001001 +

#78000
b1000000010010111011001 !
b11010011111001 "
b11000000001001 #
b1001110 $
b11010011 &
1'
b1000000010010111011001 *
b1000000010010111011001 +

#79000
b11111001010010100001000 !
b1000 "
b11010011111001 #
b1001111 $
b0 &
0'
b11111001010010100001000 *
b11111001010010100001000 +

#80000
b101011110111010011110100 !
b10100 "
b1000 #
b1010000 $
b101011110111010011110100 *
b101011110111010011110100 +

#81000
b11101011100101100101101 !
b11111111001101 "
b10100 #
b1010001 $
b11111111 &
b11101011100101100101101 *
b11101011100101100101101 +

#82000
b11010110101001000000101 !
b11011010000101 "
b11111111001101 #
b1010010 $
b11011010 &
b11010110101001000000101 *
b11010110101001000000101 +

#83000
b111111101111010011100010 !
b10 "
b11011010000101 #
b1010011 $
b0 &
b111111101111010011100010 *
b111111101111010011100010 +

#84000
b1010101011100111100000 !
b0 "
b10 #
b1010100 $
b1010101011100111100000 *
b1010101011100111100000 +

#85000
b110010000100010101011 !
b1101101011 "
b0 #
b1010101 $
b1101 &
1'
b110010000100010101011 *
b110010000100010101011 +

#86000
b101110000010000100011100 !
b11100 "
b1101101011 #
b1010110 $
b0 &
0'
b101110000010000100011100 *
b101110000010000100011100 +

#87000
b101111001011000110011111 !
b1010000011111 "
b11100 #
b1010111 $
b1010000 &
b101111001011000110011111 *
b101111001011000110011111 +

#88000
b10100101011011101111111 !
b10010001011111 "
b1010000011111 #
b1011000 $
b10010001 &
b10100101011011101111111 *
b10100101011011101111111 +

#89000
b10101011011111101111110 !
b11110 "
b10010001011111 #
b1011001 $
b0 &
b10101011011111101111110 *
b10101011011111101111110 +

#90000
b11000000011011001010000 !
b10000 "
b11110 #
b1011010 $
b11000000011011001010000 *
b11000000011011001010000 +

#91000
b1110100001011011100100 !
b100 "
b10000 #
b1011011 $
b1110100001011011100100 *
b1110100001011011100100 +

#92000
b111100011110001001111110 !
b11110 "
b100 #
b1011100 $
b111100011110001001111110 *
b111100011110001001111110 +

#93000
b110011100010110011001011 !
b1001011 "
b11110 #
b1011101 $
b1 &
b110011100010110011001011 *
b110011100010110011001011 +

#94000
b101011110110010101101111 !
b11011000001111 "
b1001011 #
b1011110 $
b11011000 &
b101011110110010101101111 *
b101011110110010101101111 +

#95000
b10011000011011110111 !
b10000011010111 "
b11011000001111 #
b1011111 $
b10000011 &
b10011000011011110111 *
b10011000011011110111 +

#96000
b110101111011101011110100 !
b10100 "
b10000011010111 #
b1100000 $
b0 &
b110101111011101011110100 *
b110101111011101011110100 +

#97000
b10110000011111001011110 !
b11110 "
b10100 #
b1100001 $
b10110000011111001011110 *
b10110000011111001011110 +

#98000
b100011000110100101011011 !
b101001011011 "
b11110 #
b1100010 $
b101001 &
b100011000110100101011011 *
b100011000110100101011011 +

#99000
b10100101011001000111011 !
b10010001011011 "
b101001011011 #
b1100011 $
b10010001 &
b10100101011001000111011 *
b10100101011001000111011 +

#100000
b110011100111001100100110 !
b110 "
b10010001011011 #
b1100100 $
b0 &
b110011100111001100100110 *
b110011100111001100100110 +

#101000
b111000000111001001110100 !
b10100 "
b110 #
b1100101 $
b111000000111001001110100 *
b111000000111001001110100 +

#102000
b110001011100101001110011 !
b101010011 "
b10100 #
b1100110 $
b101 &
b110001011100101001110011 *
b110001011100101001110011 +

#103000
b101010101100111100011001 !
b1010110011001 "
b101010011 #
b1100111 $
b1010110 &
b101010101100111100011001 *
b101010101100111100011001 +

#104000
b1011011010010011101111 !
b1000110001111 "
b1010110011001 #
b1101000 $
b1000110 &
b1011011010010011101111 *
b1011011010010011101111 +

#105000
b11001100010001011100000 !
b0 "
b1000110001111 #
b1101001 $
b0 &
b11001100010001011100000 *
b11001100010001011100000 +

#106000
b110001001100010101111111 !
b100011111 "
b0 #
b1101010 $
b100 &
b110001001100010101111111 *
b110001001100010101111111 +

#107000
b11001001111101101100010 !
b10 "
b100011111 #
b1101011 $
b0 &
b11001001111101101100010 *
b11001001111101101100010 +

#108000
b11110011101011111000100 !
b100 "
b10 #
b1101100 $
b11110011101011111000100 *
b11110011101011111000100 +

#109000
b111001001010101010111101 !
b10011101 "
b100 #
b1101101 $
b10 &
b111001001010101010111101 *
b111001001010101010111101 +

#110000
b111110010000011001011001 !
b10011001 "
b10011101 #
b1101110 $
b111110010000011001011001 *
b111110010000011001011001 +

#111000
b1011110100010010000 !
b10000 "
b10011001 #
b1101111 $
b0 &
b1011110100010010000 *
b1011110100010010000 +

#112000
b1001101011011001000000 !
b0 "
b10000 #
b1110000 $
b1001101011011001000000 *
b1001101011011001000000 +

#113000
b11001000100000101100001 !
b101011000001 "
b0 #
b1110001 $
b101011 &
b11001000100000101100001 *
b11001000100000101100001 +

#114000
b11011110101010000011101 !
b11111010011101 "
b101011000001 #
b1110010 $
b11111010 &
b11011110101010000011101 *
b11011110101010000011101 +

#115000
b110000110101000110111 !
b10100110111 "
b11111010011101 #
b1110011 $
b10100 &
1'
b110000110101000110111 *
b110000110101000110111 +

#116000
b111101000000000001100101 !
b10000101 "
b10100110111 #
b1110100 $
b10 &
0'
b111101000000000001100101 *
b111101000000000001100101 +

#117000
b110011001010011000011110 !
b11110 "
b10000101 #
b1110101 $
b0 &
b110011001010011000011110 *
b110011001010011000011110 +

#118000
b10101100001000011101111 !
b10000000001111 "
b11110 #
b1110110 $
b10000000 &
b10101100001000011101111 *
b10101100001000011101111 +

#119000
b110000000000001001101101 !
b1101 "
b10000000001111 #
b1110111 $
b0 &
b110000000000001001101101 *
b110000000000001001101101 +

#120000
b11110101111100110110111 !
b11011111010111 "
b1101 #
b1111000 $
b11011111 &
b11110101111100110110111 *
b11110101111100110110111 +

#121000
b11001100101001011010111 !
b10110110010111 "
b11011111010111 #
b1111001 $
b10110110 &
b11001100101001011010111 *
b11001100101001011010111 +

#122000
b1100001101100001000110 !
b110 "
b10110110010111 #
b1111010 $
b0 &
b1100001101100001000110 *
b1100001101100001000110 +

#123000
b101011100100101110100110 !
b110 #
b1111011 $
b101011100100101110100110 *
b101011100100101110100110 +

#124000
b1111100 $
